<?xml version="1.0" encoding="UTF-8"?>
<site>
   <description name="J2OG Update Site" url="http://jevopi.de/updatesite/de.jevopi.j2og">
      Update Site for J2OG project.
   </description>
   <feature url="features/de.jevopi.j2og.feature_0.3.1.201607142217.jar" id="de.jevopi.j2og.feature" version="0.3.1.qualifier">
      <category name="de.jevopi.j2og"/>
   </feature>
   <feature url="features/de.jevopi.j2og.emf.feature_0.1.0.201607142217.jar" id="de.jevopi.j2og.emf.feature" version="0.1.0.qualifier">
      <category name="de.jevopi.j2og"/>
   </feature>
   <category-def name="de.jevopi.j2og" label="JavaToOmniGraffle">
      <description>
         Create OmniGraffle Drawings
      </description>
   </category-def>
</site>
